ggviews/__init__.py
ggviews/additional_geoms.py
ggviews/advanced_themes.py
ggviews/brewer_scales.py
ggviews/coord_flip.py
ggviews/coords.py
ggviews/core.py
ggviews/facets.py
ggviews/geom_boxplot.py
ggviews/geom_density.py
ggviews/geom_map.py
ggviews/geom_tile.py
ggviews/geoms.py
ggviews/position_dodge.py
ggviews/positions.py
ggviews/scales.py
ggviews/stats.py
ggviews/theme_elements.py
ggviews/themes.py
ggviews/utils.py
ggviews/viridis.py
ggviews-0.2.0.dist-info/METADATA
ggviews-0.2.0.dist-info/WHEEL
ggviews-0.2.0.dist-info/top_level.txt
ggviews-0.2.0.dist-info/RECORD
