Metadata-Version: 2.4
Name: ggviews
Version: 0.2.0
Summary: ggplot2 interface to holoviews
Author-email: Essi Parent <essiparent@icloud.com>
License: MIT
Project-URL: Homepage, https://github.com/essicolo/ggviews
Project-URL: Repository, https://github.com/essicolo/ggviews
Project-URL: Documentation, https://github.com/essicolo/ggviews
Keywords: data-science,visualization,analysis
Classifier: Development Status :: 3 - Alpha
Classifier: Intended Audience :: Developers
Classifier: License :: OSI Approved :: MIT License
Classifier: Programming Language :: Python :: 3
Classifier: Programming Language :: Python :: 3.8
Classifier: Programming Language :: Python :: 3.9
Classifier: Programming Language :: Python :: 3.10
Classifier: Programming Language :: Python :: 3.11
Requires-Python: >=3.8
Requires-Dist: holoviews>=1.15.0
Requires-Dist: pandas>=1.3.0
Requires-Dist: numpy>=1.20.0
Requires-Dist: bokeh>=2.4.0
Requires-Dist: matplotlib>=3.5.0
Requires-Dist: jupyter>=1.0.0
Requires-Dist: notebook>=6.4.0
Requires-Dist: scipy>=1.7.0
Requires-Dist: scikit-learn>=1.0.0
Provides-Extra: dev
Requires-Dist: pytest>=7.0.0; extra == "dev"
Requires-Dist: black>=22.0.0; extra == "dev"
Requires-Dist: flake8>=4.0.0; extra == "dev"
Requires-Dist: mypy>=0.950; extra == "dev"
